{"body": "\nThanks, Thomas!\n\n\nOn Mon, Jul 26, 2010 at 4:20 AM, Ji Zhang <hope.zh@gmail.com> wrote:\n\nJi: Yes, Thomas, the concept as explained by you is the same as the \"Facade\nSky View Factor\" mentioned by me.\n\n\n\n\nJi: Yes, Thomas, by our understanding Vertical Daylight Factor is calculated\nbased on the illuminance value of a point on vertical surface that is the\nsum of the light coming directly from the CIE overcast sky and the light\nreflected by surrounding surfaces and ground plane.\n\n\n\n\nThank you very much for your detailed suggestion! We'll try accordingly\nlater.\n\nJi\n-------------- next part --------------\nAn HTML attachment was scrubbed...\nURL: http://radiance-online.org/pipermail/radiance-general/attachments/20100726/668039ca/attachment.htm\n", "replyTo": "<AANLkTinMgX2vNm9PRB3wq2MEdFA3LFPQp+VLgEgj2STk@mail.gmail.com>", "sender": "Ji Zhang", "isquestion": false, "tags": [], "id": "<AANLkTimjebKnFJM7Ls_38kAaDyHGt9BYvdTGjWKMnFi4@mail.gmail.com>", "refs": ["<AANLkTinu4ARdHpmWnL3M1aPFqyyot3ntD42fDPuonGF7@mail.gmail.com>", "<AANLkTinMgX2vNm9PRB3wq2MEdFA3LFPQp+VLgEgj2STk@mail.gmail.com>"], "datetime": "Mon Jul 26 05:33:01 2010", "email": "hope.zh at gmail.com", "subject": "[Radiance-general] how to split vertical illuminance level intolight coming from sky and light reflected by surface?"}