{"body": "\nOK, you are talking about run-to-run consistency.  We need to be clear on these things.\n\nTry decreasing the -lw setting as I recommended to see how this affects run-to-run differences.  There will always be some random variation, especially using the -u+ setting, but on average these should decrease with increasing calculation times.\n\nBest,\n-Greg\n\n\n", "replyTo": "Subject: [Radiance-general] Reduce rtrace runtime", "sender": "Greg Ward", "isquestion": false, "tags": [], "id": "<234EC553-7D12-4888-A8BF-A7754DAFB2DF@lmi.net>", "refs": ["<AANLkTikz6bGAFyeaYQ6KM2568H-7tG2ekFugZPk+fXFo@mail.gmail.com>", "<9ABD0CB5-5AE0-4F76-96CA-FD9E50D55878@lmi.net>", "<AANLkTimFWvStyBFNoXNR3BUVkQCKcd+B5GQ7e625vin-@mail.gmail.com>", "<9C041DFB-CA49-4841-9392-9C8A93AC619C@lmi.net>", "<AANLkTimQijuSvcShbDPV0ctkOqAd2T-AyVTjZb3eja8B@mail.gmail.com>"], "datetime": "Tue Aug 31 09:11:32 2010", "email": "gregoryjward at gmail.com", "subject": "[Radiance-general] Reduce rtrace runtime"}