{"body": "\nHi Andy,\n\nI think your roughness and absorption input labels are switched in this\nwidget.  This is a nice little tool - thanks!\n\nZack\n\nOn Fri, Apr 27, 2012 at 3:31 PM, Andy McNeil <amcneil at lbl.gov> wrote:\n\n\n\n\n--\nZack Rogers, P.E., LEED AP BD+C\nDaylighting Innovations, LLC\n211 North Public Road, Suite 220\nLafayette, CO 80026\n(303)946-2310\n-------------- next part --------------\nAn HTML attachment was scrubbed...\nURL: <http://www.radiance-online.org/pipermail/radiance-general/attachments/20120427/9ce71d95/attachment.html>\n\n", "replyTo": "<D25D89EE-E23A-4B70-B215-CCDF1AB03419@lbl.gov>", "sender": "Zack Rogers", "isquestion": false, "tags": [], "id": "<CAAP856zT8pfJW39tpHJ1WyTBQagnkRU1OgdXpsQFv7mkSuF1mg@mail.gmail.com>", "refs": ["<FF64C124-E5C3-40CF-9B99-C15140D5E9D5@gmail.com>", "<D25D89EE-E23A-4B70-B215-CCDF1AB03419@lbl.gov>"], "datetime": "Fri, 27 Apr 2012 16:17:46 -0600", "email": "zrogers at daylightinginnovations.com", "subject": "[Radiance-general] modeling an insulating glass with anintegrated capillary slab"}