{"refs": ["<001001c58cce$8878b1d0$1f7af90a@hwx>"], "id": "<20050801204811.GA4884@zwielich.escape.de>", "subject": "[Radiance-general] mapping textur", "email": "tbleicher at zwielicht.escape.de", "body": "\nOn Wed, Jul 20, 2005 at 10:58:32 +0900, Huangwx@kyotoUniv. wrote:\n\nHi Huang.\n\nSorry for the late reply, I hope you did not despaire yet.\n\nYou can find a few of the mapping types illustrated here:\n\nhttp://home.arcor.de/tbleicher/radiance/imagemaps.html#mapping_types\n\nI wrote this two years ago and can't remember where I got my\ninformation from in the first place; probably try-and-error.\n\n\nHth, Thomas\n\n\n", "isquestion": false, "replyTo": "Subject: [Radiance-general] mapping textur", "tags": [], "sender": "Thomas Bleicher", "datetime": "Tue Aug  2 00:07:59 2005"}