{"body": "\nAlejandro,\n\nsee this post a few months ago:\nhttp://radiance-online.org/pipermail/radiance-general/2014-March/010145.html\n\nRegards\nAxel\n\n\nOn 11 July 2014 10:07, Koji Takemasa <koji_takemasa at me.com> wrote:\n\n\n", "replyTo": "Subject: [Radiance-general] .pl files in Windows", "sender": "Axel Jacobs", "isquestion": false, "tags": [], "id": "<CA+dqh61D7qp-RVj4yefsQ3AGFRpEV_v367iC15PuQowRSmegqQ@mail.gmail.com>", "refs": ["<DUB128-W585F4E5FFDA19EEC33F014CA090@phx.gbl>", "<53BFA939.6040401@me.com>"], "datetime": "Fri, 11 Jul 2014 10:12:57 +0100", "email": "jacobs.axel at gmail.com", "subject": "[Radiance-general] .pl files in Windows"}