{"body": "\n\nThe info in this thread is what I used to model a wavy water surface in\nthe Basic Tutorial which is linked in here:\nhttp://luminance.londonmet.ac.uk/learnix/index.php?module=phatfile&FILE_MAN_OP=Main&MMN_position=4:4\nSee page 13.\nThe primitives are listed in the appendix.\n\n\nAxel\n\n\n\n", "replyTo": "Subject: [Radiance-general] Radiance model water", "sender": "Axel Jacobs", "isquestion": false, "tags": [], "id": "<10101.213.58.101.94.1112738010.squirrel@213.58.101.94>", "refs": ["<10C94843061E094A98C02EB77CFC328713582BF7@nrcmrdex1d.imsb.nrc.ca>", "<54858.209.212.87.250.1112732023.squirrel@209.212.87.250>"], "datetime": "Tue Apr  5 23:38:45 2005", "email": "a.jacobs at londonmet.ac.uk", "subject": "[Radiance-general] Radiance model water"}