{"refs": ["<20060803100312.4054gmx1@mx012.gmx.net>"], "id": "<44D1D06F.7010502@gmx.de>", "subject": "[Radiance-general] Re: making my own ies fil", "email": "christian_fusenig at gmx.de", "body": "\nHi Chris,\n\nArri doesn't provide IES or EULUMDAT data for their luminaires, but they\nhave a photometric calculator on their website.\nI measured four different types of luminaires for my thesis and created\nIES files, tell me which one you want, maybe i can help you.\nRegards,\n\nChristian\n\n--\n\nChristian Fusenig\nDipl.-Ing. Medientechnik\nBeim Schlump 27/07\n20144 Hamburg\nmobil: 0179/5975845\n\n\n", "isquestion": false, "replyTo": "Subject: [Radiance-general] Re: making my own ies fi", "tags": [], "sender": "Christian Fusenig", "datetime": "Thu Aug  3 12:30:09 2006"}