{"body": "\nI've upgraded to Tiger, and now I have problems changing the default to open\npic files with Photosphere\nWhat I do:\nselect a .pic file - Get info\nit will open with Preview - I tell it to open with Photosphere\nI select \"Change All\" to make all my .pic file to open with Photosphere\nI get a pop-up and I confirm that's what I want to do\nI go back to the get info screen - and its set to open with Preview.\n\ni can do it one at a time, but I can't get it to change all.\n\nAnyone have any ideas?\nI trashed ~Library/Preferences/com.apple.LaunchServices.plist\nAlso ran Disk utlilty and repaired permissions\nAny ideas?\n\nhere's some screenshots\nhttp://homepage.mac.com/rastermon/PhotoAlbum2.html\n\nBTW - Preview now opens hdr and exr files - which may be part of the problem\n\nRob F\n\n", "replyTo": "", "sender": "Fitzsimmons, Rob", "isquestion": true, "tags": [], "id": "<B8DD8375FCE2C94B9F170D9277C1FA2B8C5A60@corvallis>", "refs": [], "datetime": "Tue Aug 16 19:09:47 2005", "email": "Rob.Fitzsimmons at Summit.Fiserv.com", "subject": "[Radiance-general] Mac Tiger quirks"}