{"body": "\nHi Christoph,\n\nI have heard of the following but have no working experience with it:\n\nhttp://www.lichtplaner.com/\n\n-Jack de Valpine\n\nReinhart, Christoph wrote:\n\n\n\n", "replyTo": "Subject: [Radiance-general] Radiance plug-in for 3DS", "sender": "Jack de Valpine", "isquestion": false, "tags": [], "id": "<43A6D016.4050808@visarc.com>", "refs": ["<5910A0754536EA4AAD411AE8221C3962F482C8@nrccenexb1.nrc.ca>"], "datetime": "Mon Dec 19 16:25:21 2005", "email": "jedev at visarc.com", "subject": "[Radiance-general] Radiance plug-in for 3DS"}