{"refs": [], "id": "<dc928a050905200819v61ffa1f2ned7c56f1ab50fec@mail.gmail.com>", "subject": "[Radiance-general] rendering large space with small detail", "email": "vangelis54 at gmail.com", "body": "\nHi,\nThinking about the difference between?photorealism rendering and light\nvisualization?related in RWR chapter 1, pag 4 and 5.?I'd like to\nelucidate some questions about this topic:\nDoing so, ( procedures included below by example), is still a\nphisically based simulation?\nIs it a valid procedure to predict how natural light behaves inside this space?\nIs it a valid method to get fast, acurate and predictive daylight calculation?\n\nAnyway, I was frightened with plethora of variations and possibilities\nto solve this problem.\n\nthank you,\n\nregards\nVangelis\n\n\n", "isquestion": true, "replyTo": "", "tags": [], "sender": "Evangelos Christakou", "datetime": "Wed May 20 08:19:05 2009"}