{"refs": [], "id": "<694e132c0908120624o19cece1ds9dc3e60cd1ba6520@mail.gmail.com>", "subject": "[Radiance-general] Using SSLD skies with sun", "email": "dbs176 at gmail.com", "body": "\n\n\nThe sun hits a zenith of 90 at any position between the Tropic of\nCancer and the Tropic of Capricorn. A few degrees above and below the\ntropics hit a zenith of 87.5.\n\nA short while ago I modified and recompiled gensky, changing 87.5 to\n89.9 in lines 218-225 (\nhttp://www.radiance-online.org/pipermail/radiance-general/2005-December/003118.html\n).\n\nHas anybody else done this and run into problems?\n\nI think if the zenith is at 90.0, the -vu vector may get messy if\nyou're translating the gensky output into a camera showing the sun's\nview, which was my reasoning for 89.9.\n\n--Dave\n\n", "isquestion": true, "replyTo": "", "tags": [], "sender": "David Smith", "datetime": "Wed Aug 12 06:24:11 2009"}