{"body": "\n\nWell, for most purposes setting the clipping volume is a fine\nalternative, so it probably isn't worth worrying about this too much\nmore.  But I still don't understand how it could be happening.  Do you\nmanually specify the rays yourself and render the image with rtrace?\n\nweird ...\n\n-- Roland\n\n\nOn Apr 20, 2007, at 2:39 PM, Katja Doerschner wrote:\n\n\n\n", "replyTo": "Subject: [Radiance-general] remove light probe image from background", "sender": "Roland William Fleming", "isquestion": false, "tags": [], "id": "<31713e789f9034dac071501328ee8852@tuebingen.mpg.de>", "refs": ["<B8DD8375FCE2C94B9F170D9277C1FA2B0C23A0A4@corvallis>", "<2E27E12E-7B67-42F5-B766-7683535240AA@umn.edu>", "<0e92d5fb4642ea13d95bcc3e244a34b3@tuebingen.mpg.de>", "<4628B481.7030808@umn.edu>"], "datetime": "Fri Apr 20 16:00:06 2007", "email": "roland.fleming at tuebingen.mpg.de", "subject": "[Radiance-general] remove light probe image from background"}