{"refs": ["<4C127C30.7020208@transsolar.com>", "<6DAEF326-F5A1-4260-8D2B-E8FE6F9807A7@coolshadow.com>"], "id": "<E9A0846B-1E6F-4CFD-B9C7-BB098C14DC26@lmi.net>", "subject": "[Radiance-general] Re: Vwrays-Rtcontrib generated image agreemenwith Rpict image", "email": "gregoryjward at gmail.com", "body": "\nHi Chris,\n\nCould the -I+ option you're giving to rtcontrib be substituted with\nthe -i+ option?  The former would compute an array of irradiance\nvalues surrounding your -vp setting, rather than an irradiance image\nof intersected surfaces.  I wouldn't think the images would look very\nsimilar in this case.  Did you compare the appearance of rtcontrib -I+\nversus rpict -i?\n\n-Greg\n\n\n", "isquestion": false, "replyTo": "<6DAEF326-F5A1-4260-8D2B-E8FE6F9807A7@coolshadow.com>", "tags": [], "sender": "Greg Ward", "datetime": "Fri Jun 11 13:42:41 2010"}