{"refs": ["<FF7EFE55-A44E-11D8-943F-000A959DDB22@gmx.net>", "<Pine.SOL.4.58.0405141629160.2460@pobox.upenn.edu>", "<CA3DCE34-A5E7-11D8-B7A1-000A95BB392A@lmi.net>"], "id": "<Pine.SOL.4.58.0405141835440.25970@pobox.upenn.edu>", "subject": "[Radiance-general] color of the light sour", "email": "beixiao at mail.med.upenn.edu", "body": "\nHi, Greg\nThank you. I am generating hyperspectral images using Radiance and also\nPsychotoolBox. For right now, I rendered 24 chips of the macbeth\nchecker board to test the code of generating right color of hyperspectral\nimages. But the color of the objects come out weird because the light has a yellowish\ncolor. So everything looks yellowish.\n\nI follwed the thread of the specular reflectance. But i am not so clear\nwhat does the -st (specular thresold mean). Currently, I set the -st as\n0.1. But I found whatever falue I use for specular reflectance, the effect\nof the glossiness is not big.\n\n\nThanks,\n\nBei\n\nOn Fri, 14 May 2004, Greg Ward wrote:\n\n\n", "isquestion": false, "replyTo": "Subject: [Radiance-general] color of the light sourc", "tags": [], "sender": "Bei Xiao", "datetime": "Sat May 15 00:40:23 2004"}