{"refs": [], "id": "<CAD83LVKcnCTqNNwjA_6iU+jn1iQ99GC44pFfiuAdz_6kFu1-VA@mail.gmail.com>", "subject": "[Radiance-general] camera ball taking 360 degree panoramic photo", "email": "hope.zh at gmail.com", "body": "\nhttp://jonaspfeil.de/ballcamera\n\nThe camera ball designed by Jonas Prefli can take 360 degree panoramic\nphoto.\n\nI wander how this device can be utilized in daylight research if it can\ntake HDR photos.\n\n- Cheers, Ji\n-------------- next part --------------\nAn HTML attachment was scrubbed...\nURL: <http://www.radiance-online.org/pipermail/radiance-general/attachments/20120304/d59021a1/attachment.html>\n\n", "isquestion": true, "replyTo": "", "tags": [], "sender": "Ji Zhang", "datetime": "Sun, 4 Mar 2012 23:35:45 +0800"}