{"refs": ["<CAD7gt0WfTisi0_D4HkxP+g3UxCisjBmBT3pJDrN5wt7Si_NWGQ@mail.gmail.com>", "<7F2DA804-837E-41E7-B928-F0561FBA1D95@lmi.net>", "<CAD7gt0U==iDAaMmMbnK4PMs7rYd6wOeyyKGiawiL_B8YNp8FSA@mail.gmail.com>", "<E9833256-DA09-4D55-BF3F-FBB1BFC6EF51@lmi.net>", "<CAD7gt0Wx9bsuE2sJBkEji3fw_4Oo2vm00T4QU=eb_b9R_UWEzw@mail.gmail.com>"], "id": "<6EFC15DE-66B2-47F1-8D6A-E1E3C890800B@lmi.net>", "subject": "[Radiance-general] Where does bgraph look for .plt files?", "email": "gregoryjward at gmail.com", "body": "\nThat is very strange in that case.  What happens when you run the following:\n\ncsh -f -c 'ls -l ${MDIR}line.plt'\n\nYou should see something like:\n\n-rw-r--r--  1 gward  admin  728 Feb 13  1990   /usr/share/radiance/meta/line.plt\n\n...only with your user name, obviously.  Make sure the file is readable.  The contents of the file should be:\n\n#\n#\tThis file defines a standard line plot,\n#\twhere a curve is represented by lines\n#\tconnecting each point.\n#\n\ninclude = standard.plt\t\t# standard definitions\n\nlthick = 2\t# line thickness\n\n(...and so on...)\n\nI can't think what else might be wrong.\n\n-Greg\n\n-------------- next part --------------\nAn HTML attachment was scrubbed...\nURL: <http://www.radiance-online.org/pipermail/radiance-general/attachments/20140415/7d1fd971/attachment.html>\n\n", "isquestion": false, "replyTo": "Subject: [Radiance-general] Where does bgraph look for .plt files?", "tags": [], "sender": "Greg Ward", "datetime": "Tue, 15 Apr 2014 11:36:38 -0700"}