{"body": "\nIsn't the internal efficacy 179?\n\n-Jack\n\nIgnacio Munarriz wrote:\n\n\n--\n# Jack de Valpine\n# president\n#\n# visarc incorporated\n# http://www.visarc.com\n#\n# channeling technology for superior design and construction\n\n\n", "replyTo": "<4ACC72C4.4030301@aisarquitectura.com>", "sender": "Jack de Valpine", "isquestion": false, "tags": [], "id": "<4ACC877E.4070408@visarc.com>", "refs": ["<4ACC4C37.9030607@gmx.net>", "<4ACC61D0.5050907@aisarquitectura.com>\t<4ACC6697.8070708@gmx.net>", "<4ACC72C4.4030301@aisarquitectura.com>"], "datetime": "Wed Oct  7 05:20:24 2009", "email": "jedev at visarc.com", "subject": "[Radiance-general] getting irradiance from source defined inphotometric units"}