{"body": "German\n\n\nHave you tried to change the geometry identifier in the IES file to\nindicate a box geometry. I am a bit rusty on the specs but I don't think\nanything else depends on this information so the change should be simple to\ndo. The transformation in a Radiance box is then done by ies2rad.\n\n\nRegards,\nThomas\n\n\nOn Fri, Aug 7, 2015 at 1:09 PM, Germ\u00e1n Molina Larrain <germolinal at gmail.com>\n___\n<sup>Automatically generated content from [radiance mailing-list](https://radiance-online.org/pipermail/radiance-general/2015-November/011336.html).</sup>", "attachments": [], "created_by_name": "Thomas Bleicher", "created_at": "November 11, 2015 at 05:46PM", "created_by": "Thomas_Bleicher", "parent_id": "radiance-general_011161", "id": "radiance-general_011336"}