{"body": "Ji,\n\n\nMy suggestion is to simplify your command.  Most of your time is probably being spent in pcomb, unless your scene is extremely complex.  Try:\n\n\n\toconv -f ./plastic_mat.rad ./geom.rad \\\n\t| rpict -av 1 1 1 -vf view_vts.vf -x 1000 -y 1000 \\\n\t| pcomb -e 'lo=if(gi(1),0,S(1))' - \\\n\t| pvalue -h -H -pG -d \\\n\t| total \\\n\t| rcalc -e '$1=$1/2/PI' > ./SkyEF_results.txt\n\n\nBest,\n-Greg\n___\n<sup>Automatically generated content from [radiance mailing-list](https://radiance-online.org/pipermail/radiance-general/2012-December/009080.html).</sup>", "attachments": [], "created_by_name": "Greg Ward", "created_at": "December 01, 2012 at 10:26AM", "created_by": "Greg_Ward", "parent_id": "radiance-general_008984", "id": "radiance-general_009080"}