{"body": "I can attest that ies2rad doesn't know about these \"tricks,\" as I \ndidn't know about these tricks.  I don't think I'll have time to fix it \nin the immediate future, and given that I still don't understand the \nsubtleties involved, I wouldn't want to attempt a quick hack in this \ncase.  It sounds like Schorsch is definitely onto something, though...\n\n\n-Greg\n___\n<sup>Automatically generated content from [radiance mailing-list](https://radiance-online.org/pipermail/radiance-general/2004-June/001812.html).</sup>", "attachments": [], "created_by_name": "Greg Ward", "created_at": "June 12, 2004 at 04:09PM", "created_by": "Greg_Ward", "parent_id": "radiance-general_001805", "id": "radiance-general_001812"}