{"body": "Thanks Andrew,\n\n\nyes if i give -ab 1 is direct calculation only then it is working.....\n\u00a0\nBest Regards,     Brajesh Lal\n\n\n\n\n________________________________\n___\n<sup>Automatically generated content from [radiance mailing-list](https://radiance-online.org/pipermail/radiance-general/2013-March/009397.html).</sup>", "attachments": [], "created_by_name": "Brajesh Lal", "created_at": "March 15, 2013 at 10:27AM", "created_by": "Brajesh_Lal", "parent_id": "radiance-general_009384", "id": "radiance-general_009397"}