{"body": "I am running the latest HEAD release and am getting a Segmentation fault \nwhen I try to use illums.  Without the illums, everything runs fine.  Has \nanyone else experienced this?  In addition, when I run it with the official \nrelease, the model with the illums run fine.\n\n\n_________________________________________________________________\nCheck out the coupons and bargains on MSN Offers! \nhttp://shopping.msn.com/softcontent/softcontent.aspx?scmId=1418\n___\n<sup>Automatically generated content from [radiance mailing-list](https://radiance-online.org/pipermail/radiance-general/2004-January/001433.html).</sup>", "attachments": [], "created_by_name": "etienne canard", "created_at": "January 20, 2004 at 12:29PM", "created_by": "etienne_canard", "parent_id": "radiance-general_001434", "id": "radiance-general_001433"}