{"body": "Hi Alstan,\n\n\nyou can use also this command (should be possible also under windows, \nwhen you have installed the sed, shoould be part of mingw):\n\n\nsed -e 's/    VIEW/VIEW/g'  input.hdr >output.hdr\n\n\nThe character before the first \"VIEW\" must be a TAB.\n\n\nbest,\n\n\nJan\n\n\n\n\nOn 03/10/2014 04:28 AM, J. Alstan Jakubiec wrote:\n> Hi Axel,\n>\n> Thanks for the script and your reply! I'm on Windows without a Perl \n> interpreter, but its easy enough to scan to the end of the header in \n> Python / other scripting language and append the view info.\n>\n> Separately, I now realize I am actually not subscribed to the HDRI \n> list. All this time I thought it was a ghost town like the Daysim list.\n>\n> Cheers,\n> Alstan\n>\n> On Sun, 09 Mar 2014 12:44:14 -0400, Axel Jacobs \n> <jacobs.axel at gmail.com> wrote:\n>\n>> Hi Alstan,\n>>\n>> see my post to HDRI from a few days ago:\n>> http://radiance-online.org/pipermail/hdri/2014-February/000515.html\n>>\n>> Scroll down to 'c) fix the view'\n>>\n>> Best\n>>\n>> Axel\n>>\n>>\n>> On 09/03/14 16:32, J. Alstan Jakubiec wrote:\n>>> Dear List,\n>>>\n>>> These days I am doing a lot of image processing with pcomb and\n>>> expressions using the -e option. I want to save the images I parse\n>>> through pcomb for later analysis.\n>>>\n>>> The small problem with this is that pcomb removes the view information\n>>> from the header. Right now the only option I can find is to manually\n>>> append my original view information to the new file's header. Is there,\n>>> by chance, an option to maintain the view information when using pcomb?\n>>> Its not a problem for me to automate this, but it is nice to stay \n>>> within\n>>> the Radiance toolkit if possible.\n>>>\n>>> Thanks very much,\n>>> Alstan\n>>>\n>>> _______________________________________________\n>>> Radiance-general mailing list\n>>> Radiance-general at radiance-online.org\n>>> http://www.radiance-online.org/mailman/listinfo/radiance-general\n>>\n>>\n>> _______________________________________________\n>> Radiance-general mailing list\n>> Radiance-general at radiance-online.org\n>> http://www.radiance-online.org/mailman/listinfo/radiance-general\n>\n> _______________________________________________\n> Radiance-general mailing list\n> Radiance-general at radiance-online.org\n> http://www.radiance-online.org/mailman/listinfo/radiance-general\n\n\n\n\n\n\nDr.-Ing. Jan Wienold\nHead of Team Passive Systems and Daylighting\nFraunhofer-Institut f\u00fcr Solare Energiesysteme\nThermal Systems and Buildings\nHeidenhofstr. 2, 79110 Freiburg, Germany\nPhone: +49(0)761 4588 5133 Fax:+49(0)761 4588 9133\njan.wienold at ise.fraunhofer.de\nhttp://www.ise.fraunhofer.de\n\n\nIn office:\nMo,Tue: 8:30-18:00\nWe,Thu: 8:30-16:00\nFr:  8:30-15:30\n___\n<sup>Automatically generated content from [radiance mailing-list](https://radiance-online.org/pipermail/radiance-general/2014-March/010149.html).</sup>", "attachments": [], "created_by_name": "Jan Wienold", "created_at": "March 10, 2014 at 04:01AM", "created_by": "Jan_Wienold", "parent_id": "radiance-general_010144", "id": "radiance-general_010149"}