{"topic": "LightStanza: 2 free talks in San Francisco June 25 and June 26th", "category": "radiance-general", "attachments": [], "created_by_name": "Daniel Glaser", "created_at": "June 11, 2015 at 10:29PM", "body": "Dear Radiance Colleagues,\n\n\nI will be giving two FREE talks on daylighting at the Pacific Energy Center\nin San Francisco this month.  On June 25, I will be presenting an evening\nlecture on the current annual metrics, discussing their strengths,\nlimitations, assumptions and controversies, including their applications in\nthe new LEED v4.  This lecture will also be simulcast online.  On June 26,\nI will be giving a hands-on training workshop on LightStanza, our new\nWeb-Application for Radiance-based daylight simulation and analysis.  An\noverview video of this software is at:\n\n\nhttps://youtu.be/ju6hn3FyIz4\n\n\nRegistration links (which include longer descriptions and detailed agendas)\nfor both events are listed below.  I hope you can join me!\n\n\nDaylight Deconstructed: A Visual Understanding of Sustainability Metrics\nand How to Apply Them\n\n\nThursday June 25, 2015\n\n\n6:30pm - 8:00pm\n\n\nAIA 1.5 LU/HSW Hours\n\n\nRegister:\nhttps://pge-web.ungerboeck.com/classcalendar/Details.aspx?OrgCode=10&EventId=11648\n\n\nor to join the online simulcast, register:\nhttp://lightstanza.com/GTMregistrationform.html\n\n\nStreamlining Daylight Analysis In The Cloud\n\n\nFriday June 26, 2015\n\n\n9:00am - 3:00pm\n\n\nRegister: http://lightstanza.com/registerform.html\n\n\nThanks,\n\n\nDan\n\n\n\n\n\n\nDaniel C. Glaser, PhD, LEED AP BD+C, IESPrincipal\nLight Foundry, LLC*Creators of LightStanza.com*\nBoulder, Colorado\n\n\nDirect: +1.510.387.8890Main: +1.720.722.0771\n\n\nwww.lightstanza.com\n___\n<sup>Automatically generated content from [radiance mailing-list](https://radiance-online.org/pipermail/radiance-general/2015-June/011002.html).</sup>", "id": "radiance-general_011002", "created_by": "Daniel_Glaser"}