{"topic": "Changing north direction in Daysim", "category": "radiance-daysim", "attachments": [], "created_by_name": "Mostapha Sadeghipour", "created_at": "October 22, 2014 at 09:02AM", "body": "Hi all,\n\n\nIs there a way to set up an angle for north without rotating the model in\nDaysim?\n\n\nI assume there should be a keyword in the header file that I don't know of?\nOr can I just play with time_zone and will the see the same effect?\n\n\nThanks,\nMostapha\n___\n<sup>Automatically generated content from [radiance mailing-list](https://radiance-online.org/pipermail/radiance-daysim/2014-October/000078.html).</sup>", "id": "radiance-daysim_000078", "created_by": "Mostapha_Sadeghipour"}